{"name": "Родившиеся_в_Дагестане", "id": 1214808, "predecessors": [{"name": "Родившиеся_в_России", "id": 770299}, {"name": "Всё", "id": 16350}], "successors": [{"name": "Родившиеся_в_Дербенте", "id": 299076}, {"name": "Родившиеся_в_Махачкале", "id": 784248}, {"name": "Родившиеся_в_Каспийске", "id": 863549}, {"name": "Родившиеся_в_Хасавюрте", "id": 865024}, {"name": "Родившиеся_в_Буйнакске", "id": 1522260}, {"name": "Родившиеся_в_Кизляре", "id": 1942945}, {"name": "Родившиеся_в_Кизилюрте", "id": 2656181}, {"name": "Родившиеся_в_Хасавюртовском_районе", "id": 4864643}, {"name": "Родившиеся_в_Лакском_районе", "id": 4866817}, {"name": "Родившиеся_в_Шамильском_районе", "id": 5175635}, {"name": "Родившиеся_в_Цумадинском_районе", "id": 5274706}]}