{"name": "Награды_субъектов_Российской_Федерации", "id": 1536561, "predecessors": [{"name": "Культура_России", "id": 30220}], "successors": [{"name": "Кавалеры_ордена_«За_заслуги_перед_Ростовской_областью»", "id": 4837792}, {"name": "Почётные_граждане_Удмуртской_Республики", "id": 5027385}, {"name": "Лауреаты_государственной_премии_Удмуртской_Республики", "id": 9135515}, {"name": "Кавалеры_ордена_Республики_Тыва", "id": 5476797}, {"name": "Народные_писатели_Дагестана", "id": 3112235}, {"name": "Народные_артисты_Дагестана", "id": 6193047}, {"name": "Заслуженные_деятели_науки_Республики_Дагестан", "id": 6884427}, {"name": "Удостоенные_звания_«Народный_герой_Дагестана»", "id": 7763694}, {"name": "Кавалеры_ордена_«За_заслуги_перед_Республикой_Татарстан»", "id": 1539204}, {"name": "Кавалеры_ордена_«Дуслык»", "id": 6772780}]}