{"name": "Исторические_области_Грузии", "id": 161908, "predecessors": [{"name": "История_Грузии", "id": 13346}, {"name": "Всё", "id": 16350}], "successors": [{"name": "Тао-Кларджети", "id": 8274542}, {"name": "Правители_Мегрелии", "id": 1432563}, {"name": "Населённые_пункты_Местийского_муниципалитета", "id": 2156992}, {"name": "Населённые_пункты_Зугдидского_муниципалитета", "id": 3321914}, {"name": "Населённые_пункты_Сенакского_муниципалитета", "id": 7755756}, {"name": "Населённые_пункты_Абашского_муниципалитета", "id": 8940603}, {"name": "Населённые_пункты_Мартвильского_муниципалитета", "id": 9259590}]}