{"name": "Университеты_Германии", "id": 163238, "predecessors": [{"name": "Высшие_учебные_заведения", "id": 19289}, {"name": "Культура_Германии", "id": 29289}], "successors": [{"name": "Выпускники_Боннского_университета", "id": 2660557}, {"name": "Преподаватели_Боннского_университета", "id": 2774469}, {"name": "Почётные_доктора_Боннского_университета", "id": 4712193}, {"name": "Выпускники_Лейпцигского_университета", "id": 789852}, {"name": "Преподаватели_Лейпцигского_университета", "id": 3004231}, {"name": "Ректоры_Лейпцигского_университета", "id": 4705880}, {"name": "Почётные_доктора_Лейпцигского_университета", "id": 4711142}, {"name": "Выпускники_Гиссенского_университета", "id": 4512985}, {"name": "Преподаватели_Гиссенского_университета", "id": 4704379}, {"name": "Почётные_доктора_Гиссенского_университета", "id": 5122151}, {"name": "Выпускники_Грайфсвальдского_университета", "id": 4706344}, {"name": "Преподаватели_Грайфсвальдского_университета", "id": 4707217}, {"name": "Почётные_доктора_Грайфсвальдского_университета", "id": 4711235}, {"name": "Выпускники_Вестфальского_университета_имени_Вильгельма", "id": 4513808}, {"name": "Преподаватели_Вестфальского_университета_имени_Вильгельма", "id": 4807920}, {"name": "Почётные_доктора_Вестфальского_университета_имени_Вильгельма", "id": 4810786}, {"name": "Преподаватели_Майнцского_университета", "id": 4958120}, {"name": "Выпускники_Майнцского_университета", "id": 5284524}, {"name": "Франкфуртская_школа", "id": 244923}, {"name": "Преподаватели_Франкфуртского_университета_имени_Иоганна_Вольфганга_Гёте", "id": 4711306}, {"name": "Выпускники_Франкфуртского_университета_имени_Иоганна_Вольфганга_Гёте", "id": 4711490}, {"name": "Почётные_доктора_Франкфуртского_университета_имени_Иоганна_Вольфганга_Гёте", "id": 5420743}, {"name": "Выпускники_Фрайбергской_горной_академии", "id": 5636975}, {"name": "Преподаватели_Ростокского_университета", "id": 4708440}, {"name": "Выпускники_Ростокского_университета", "id": 4709128}, {"name": "Почётные_доктора_Ростокского_университета", "id": 4711137}, {"name": "Почётные_доктора_Гамбургского_университета", "id": 4710761}, {"name": "Почётные_доктора_Гейдельбергского_университета", "id": 4710844}, {"name": "Почётные_доктора_Свободного_университета_Берлина", "id": 4710946}, {"name": "Почётные_доктора_Вюрцбургского_университета", "id": 4710987}, {"name": "Почётные_доктора_Йенского_университета", "id": 4711135}, {"name": "Почётные_доктора_Марбургского_университета", "id": 4711298}, {"name": "Почётные_доктора_Фрайбургского_университета", "id": 4711521}, {"name": "Почётные_доктора_Тюбингенского_университета", "id": 4711527}, {"name": "Почётные_доктора_Берлинского_университета", "id": 4711543}, {"name": "Почётные_доктора_Гёттингенского_университета", "id": 4711551}, {"name": "Почётные_доктора_Дрезденского_технического_университета", "id": 4711559}, {"name": "Почётные_доктора_Кильского_университета", "id": 4912302}, {"name": "Почётные_доктора_Галле-Виттенбергского_университета", "id": 5349987}, {"name": "Почётные_доктора_Мюнхенского_технического_университета", "id": 5442228}, {"name": "Почётные_доктора_Кёнигсбергского_университета", "id": 5635140}, {"name": "Почётные_доктора_Мюнхенского_университета", "id": 7001045}, {"name": "Почётные_доктора_Берлинского_технического_университета", "id": 7561502}, {"name": "Выпускники_Эрлангенского_университета", "id": 4589819}, {"name": "Преподаватели_Эрлангенского_университета", "id": 5633386}, {"name": "Выпускники_Вюрцбургского_университета", "id": 4513362}, {"name": "Преподаватели_Вюрцбургского_университета", "id": 4776212}, {"name": "Выпускники_Альтдорфского_университета", "id": 4785917}, {"name": "Выпускники_Берлинского_университета_искусств", "id": 10245125}, {"name": "Преподаватели_Берлинского_университета_искусств", "id": 10245191}, {"name": "Преподаватели_Берлинской_высшей_школы_музыки", "id": 4704453}, {"name": "Преподаватели_Рейнско-Вестфальского_технического_университета_Ахена", "id": 10287964}, {"name": "Выпускники_Рейнско-Вестфальского_технического_университета_Ахена", "id": 10400496}, {"name": "Выпускники_Ингольштадтского_университета", "id": 10401527}, {"name": "Выпускники_Академии_драматического_искусства_Эрнста_Буша", "id": 10402826}, {"name": "Выпускники_Берлинского_технического_университета", "id": 4893510}, {"name": "Преподаватели_Берлинского_технического_университета", "id": 5332517}, {"name": "Выпускники_Дюссельдорфской_академии_художеств", "id": 7456003}]}