{"name": "Спортивные_призы_и_награды", "id": 1829936, "predecessors": [{"name": "Символы", "id": 21767}, {"name": "Всё", "id": 16350}], "successors": [{"name": "Футбольные_награды", "id": 85998}, {"name": "Хоккейные_призы_и_награды", "id": 1829919}, {"name": "Обладатели_Приза_имени_Лу_Марша", "id": 4043668}, {"name": "Спортсмены_года_«Ассошиэйтед_Пресс»", "id": 10373757}, {"name": "Титулы_го", "id": 767987}, {"name": "Члены_Зала_славы_баскетбола", "id": 2225804}, {"name": "Члены_Зала_славы_ФИБА", "id": 2225818}, {"name": "Баскетбольные_награды_NCAA", "id": 8908030}, {"name": "Международные_гроссмейстеры_по_шашкам", "id": 4996591}, {"name": "Международные_мастера_по_шашкам", "id": 5269509}, {"name": "Гроссмейстеры_России_по_шашкам", "id": 10234704}, {"name": "Кандидаты_в_мастера_спорта_СССР", "id": 4684102}, {"name": "Кандидаты_в_мастера_спорта_России", "id": 6399197}, {"name": "Кавалеры_Олимпийского_ордена", "id": 753791}, {"name": "Заслуженные_тренеры_СССР", "id": 75226}, {"name": "Заслуженные_тренеры_России", "id": 173841}, {"name": "Заслуженные_тренеры_Украины", "id": 704859}, {"name": "Заслуженные_тренеры_Республики_Беларусь", "id": 2900027}, {"name": "Заслуженные_тренеры_Республики_Казахстан", "id": 4287063}, {"name": "Заслуженные_работники_физической_культуры_Российской_Федерации", "id": 752749}, {"name": "Заслуженные_работники_физической_культуры_и_спорта_Украины", "id": 3996437}, {"name": "Заслуженные_деятели_физической_культуры_и_спорта_Азербайджана", "id": 7265292}, {"name": "Заслуженные_работники_физической_культуры_РСФСР", "id": 750494}, {"name": "Заслуженные_тренеры_Узбекской_ССР", "id": 3267403}, {"name": "Обладатели_Кубка_мира_по_горнолыжному_спорту_в_общем_зачёте", "id": 1497331}, {"name": "Обладатели_Кубка_мира_по_лыжным_гонкам", "id": 1824458}, {"name": "Обладатели_Кубка_мира_по_бобслею", "id": 4419071}, {"name": "Обладатели_Кубка_мира_по_горнолыжному_спорту", "id": 4419170}, {"name": "Обладатели_Кубка_мира_по_борьбе", "id": 6428191}, {"name": "Мастера_спорта_по_шашкам", "id": 4667224}, {"name": "Списки_заслуженных_мастеров_спорта_СССР", "id": 788255}, {"name": "Списки_заслуженных_мастеров_спорта_России", "id": 801284}, {"name": "Награды_НХЛ", "id": 2626866}, {"name": "ФИФА_100", "id": 129327}]}