{"name": "Шаблоны:Ссылки_на_отдельные_книги", "id": 1950698, "predecessors": [{"name": "Шаблоны:Книги", "id": 4634149}, {"name": "Шаблоны:Ссылки_на_источники", "id": 4635873}], "successors": [{"name": "Шаблоны:Книги_о_персоналиях", "id": 2492604}, {"name": "Шаблоны:Ссылки_на_книги,_доступные_онлайн", "id": 4144370}, {"name": "Шаблоны:Справочники_и_энциклопедии", "id": 4634393}, {"name": "Шаблоны:Книги_по_военному_делу", "id": 4634210}, {"name": "Шаблоны:Книги_по_музыке", "id": 5306815}, {"name": "Шаблоны:Книги_о_ядерном_оружии", "id": 10276335}]}