{"name": "Похороненные_в_Германии", "id": 2535361, "predecessors": [{"name": "Персоналии:Германия", "id": 30383}, {"name": "Всё", "id": 16350}], "successors": [{"name": "Похороненные_в_Берлине", "id": 2143311}, {"name": "Похороненные_в_Бранденбурге", "id": 4692933}, {"name": "Похороненные_в_Баварии", "id": 4693044}, {"name": "Похороненные_в_Рейнланд-Пфальце", "id": 4693230}, {"name": "Похороненные_в_Баден-Вюртемберге", "id": 4693235}, {"name": "Похороненные_в_Нижней_Саксонии", "id": 4693257}, {"name": "Похороненные_в_Северном_Рейне-Вестфалии", "id": 4693268}, {"name": "Похороненные_в_Шлезвиг-Гольштейне", "id": 4693303}, {"name": "Похороненные_в_Галле_(Саксония-Анхальт)", "id": 5333051}, {"name": "Похороненные_в_Дармштадте", "id": 4693604}, {"name": "Похороненные_на_Франкфуртском_главном_кладбище", "id": 6816597}, {"name": "Похороненные_на_Русском_кладбище_в_Висбадене", "id": 8136203}, {"name": "Похороненные_в_Дрездене", "id": 4693129}, {"name": "Похороненные_в_Веймаре", "id": 4693494}, {"name": "Похороненные_в_Штутгарте", "id": 4692975}, {"name": "Похороненные_в_Кобурге", "id": 4693001}, {"name": "Похороненные_на_Ольсдорфском_кладбище", "id": 5096858}, {"name": "Похороненные_на_Южном_кладбище_(Лейпциг)", "id": 5001993}, {"name": "Похороненные_на_Новом_кладбище_Святого_Иоанна", "id": 7797237}, {"name": "Похороненные_на_кладбище_Фридрихсфельде", "id": 2143309}, {"name": "Похороненные_на_кладбище_Тегель", "id": 3492287}, {"name": "Похороненные_на_кладбище_Вальдфридхоф_(Мюнхен)", "id": 4030377}, {"name": "Похороненные_на_кладбище_Мелатен", "id": 4694644}, {"name": "Похороненные_на_Инвалиденфридхоф", "id": 4695870}, {"name": "Похороненные_на_Еврейском_кладбище_(Берлин)", "id": 4850876}, {"name": "Похороненные_на_Доротеенштадтском_кладбище", "id": 5072121}, {"name": "Похороненные_на_Далемском_лесном_кладбище", "id": 5074181}, {"name": "Похороненные_на_Юго-Западном_кладбище_(Штансдорф)", "id": 5339598}, {"name": "Похороненные_на_кладбище_Хеерштрассе", "id": 5339873}, {"name": "Похороненные_на_Целендорфском_лесном_кладбище", "id": 5343100}, {"name": "Похороненные_на_Гёттингенском_городском_кладбище", "id": 5434259}, {"name": "Похороненные_на_Старом_южном_кладбище", "id": 7097772}, {"name": "Похороненные_на_Гейдельбергском_нагорном_кладбище", "id": 7532429}, {"name": "Похороненные_на_Старом_кладбище_церкви_Святого_Матфея", "id": 8141703}]}