{"name": "Навигационные_шаблоны:США", "id": 2826767, "predecessors": [{"name": "Шаблоны:США", "id": 1139874}, {"name": "Навигационные_шаблоны:География", "id": 4767550}], "successors": [{"name": "Навигационные_шаблоны:История_США", "id": 3371137}, {"name": "Навигационные_шаблоны:Политика_США", "id": 3481626}, {"name": "Навигационные_шаблоны:Спорт_в_США", "id": 4283385}, {"name": "Навигационные_шаблоны:Персоналии_США", "id": 4587386}, {"name": "Навигационные_шаблоны:География_Аляски", "id": 5716009}, {"name": "Навигационные_шаблоны:Округа_Калифорнии", "id": 10346900}, {"name": "Навигационные_шаблоны:Округа_Флориды", "id": 10347541}, {"name": "Навигационные_шаблоны:Округа_Миннесоты", "id": 10348124}, {"name": "Навигационные_шаблоны:Округа_Юты", "id": 10347232}, {"name": "Навигационные_шаблоны:Округа_Нью-Мексико", "id": 10137465}, {"name": "Навигационные_шаблоны:Округа_Колорадо", "id": 10598123}, {"name": "Навигационные_шаблоны:Телевидение_в_США", "id": 4915734}]}