{"name": "Актрисы_Великобритании", "id": 293201, "predecessors": [{"name": "Актёры_Великобритании", "id": 50010}, {"name": "Всё", "id": 16350}, {"name": "Женщины_по_странам", "id": 1232119}], "successors": [{"name": "Порноактрисы_Великобритании", "id": 1499676}, {"name": "Актрисы_телевидения_Великобритании", "id": 4625442}, {"name": "Актрисы_театра_Великобритании", "id": 5654468}, {"name": "Киноактрисы_Великобритании", "id": 5678825}, {"name": "Актрисы_озвучивания_Великобритании", "id": 6336616}]}