{"name": "Персоналии:Кыргызстан", "id": 34421, "predecessors": [{"name": "Всё", "id": 16350}, {"name": "Календарь", "id": 10437}], "successors": [{"name": "Политики_Кыргызстана", "id": 34420}, {"name": "Поэты_Кыргызстана", "id": 142073}, {"name": "Писатели_Кыргызстана", "id": 151022}, {"name": "Родившиеся_в_Кыргызстане", "id": 1451313}, {"name": "Юристы_Кыргызстана", "id": 3564019}, {"name": "Переводчики_Кыргызстана", "id": 4036516}, {"name": "Киргизские_военачальники", "id": 10398500}, {"name": "Лауреаты_Государственной_премии_Киргизской_ССР_имени_Токтогула_Сатылганова", "id": 3560198}, {"name": "Умершие_в_Бишкеке", "id": 1274450}, {"name": "Первые_секретари_районных_комитетов_КП_Киргизской_ССР", "id": 6895609}, {"name": "Члены_ЦК_КП_Киргизской_ССР", "id": 6663331}, {"name": "Герои_Кыргызской_Республики", "id": 1262027}, {"name": "Награждённые_Почётной_грамотой_Президиума_Верховного_Совета_Киргизской_ССР", "id": 7220332}, {"name": "Награждённые_Почётной_грамотой_Кыргызской_Республики", "id": 10289219}, {"name": "Кавалеры_ордена_«Данакер»", "id": 745332}, {"name": "Кавалеры_ордена_«Манас»_III_степени", "id": 7132121}, {"name": "Кавалеры_ордена_«Манас»_II_степени", "id": 7132123}, {"name": "Кавалеры_ордена_«Манас»_I_степени", "id": 7132125}, {"name": "Награждённые_медалью_«Данк»", "id": 4595770}, {"name": "Народные_артисты_Кыргызской_Республики", "id": 1324085}, {"name": "Заслуженные_деятели_культуры_Кыргызской_Республики", "id": 4036518}, {"name": "Заслуженные_деятели_науки_Кыргызской_Республики", "id": 6446984}, {"name": "Заслуженные_деятели_искусств_Киргизской_ССР", "id": 941316}, {"name": "Народные_артисты_Киргизской_ССР", "id": 1324092}, {"name": "Заслуженные_артисты_Киргизской_ССР", "id": 1370152}, {"name": "Персоналии:Кыргызский_театр_оперы_и_балета", "id": 3287424}, {"name": "Футболисты_Кыргызстана", "id": 1683289}, {"name": "Футбольные_тренеры_Кыргызстана", "id": 2833293}, {"name": "Игроки_ФК_«Динамо_МВД»", "id": 2280521}, {"name": "Игроки_ФК_«Абдыш-Ата»", "id": 3529073}, {"name": "Игроки_ФК_«Дордой»", "id": 3969833}, {"name": "Игроки_ФК_«Алга»", "id": 4735731}, {"name": "Игроки_ФК_«Алай»", "id": 4880058}, {"name": "Игроки_ФК_«Нефтчи»_Кочкор-Ата", "id": 5299296}, {"name": "Игроки_ФК_«Жаштык-Ак-Алтын»", "id": 5962164}, {"name": "Игроки_ФК_«СКА-Достук»", "id": 6639048}, {"name": "Игроки_ФК_«Кара-Балта»", "id": 7259805}, {"name": "Игроки_сборной_Кыргызстана_по_футболу", "id": 1748460}, {"name": "Борцы_Кыргызстана", "id": 1964997}]}