{"name": "Телесериалы_США_1990-х_годов", "id": 4264957, "predecessors": [{"name": "История_США", "id": 9668}, {"name": "Всё", "id": 16350}, {"name": "Средства_массовой_информации", "id": 34710}], "successors": [{"name": "Телесериалы_США,_запущенные_в_1999_году", "id": 4611082}, {"name": "Телесериалы_США,_запущенные_в_1998_году", "id": 4660480}, {"name": "Телесериалы_США,_запущенные_в_1997_году", "id": 4660487}, {"name": "Телесериалы_США,_запущенные_в_1996_году", "id": 4660553}, {"name": "Телесериалы_США,_запущенные_в_1993_году", "id": 4672119}, {"name": "Телесериалы_США,_завершённые_в_1999_году", "id": 5301165}, {"name": "Телесериалы_США,_завершённые_в_1998_году", "id": 5301346}]}