{"name": "Изобретатели_и_рационализаторы", "id": 6819385, "predecessors": [{"name": "Всё", "id": 16350}], "successors": [{"name": "Музыкальные_конструкторы_и_изобретатели", "id": 92140}, {"name": "Изобретатели_систем_письма", "id": 256101}, {"name": "Изобретатели_по_алфавиту", "id": 287443}, {"name": "Вымышленные_изобретатели", "id": 1269601}, {"name": "Награждённые_медалью_Джона_Скотта", "id": 10020016}, {"name": "Изобретатели_XX_века", "id": 6225459}, {"name": "Изобретатели_XIX_века", "id": 6314964}, {"name": "Изобретатели_XXI_века", "id": 6866305}]}