{"name": "Родившиеся_в_Тамбовской_области", "id": 705340, "predecessors": [{"name": "Родившиеся_в_России", "id": 770299}, {"name": "Всё", "id": 16350}], "successors": [{"name": "Родившиеся_в_Тамбове", "id": 278569}, {"name": "Родившиеся_в_Моршанске", "id": 796910}, {"name": "Родившиеся_в_Мичуринске", "id": 1740616}, {"name": "Родившиеся_в_Рассказове", "id": 3536933}, {"name": "Родившиеся_в_Тамбовском_районе", "id": 4415557}, {"name": "Родившиеся_в_Сосновском_районе_(Тамбовская_область)", "id": 5433758}, {"name": "Родившиеся_в_Моршанском_районе", "id": 6127006}, {"name": "Родившиеся_в_Инжавинском_районе", "id": 6129888}]}