{"name": "Биология", "id": 8226, "predecessors": [{"name": "Всё", "id": 16350}], "successors": [{"name": "Биологическое_оружие", "id": 45687}, {"name": "Методы_биологических_исследований", "id": 267937}, {"name": "Биоэтика", "id": 281944}, {"name": "Разделы_биологии", "id": 335641}, {"name": "История_биологии", "id": 1325868}, {"name": "Популяризация_биологии", "id": 1345093}, {"name": "Книги_по_биологии", "id": 1506444}, {"name": "Электронные_биологические_ресурсы", "id": 2299805}, {"name": "Биологическая_терминология", "id": 7313328}, {"name": "Биологическая_номенклатура", "id": 8429250}, {"name": "Авторы_учебников_по_биологии", "id": 7525672}, {"name": "Списки:Ботаника", "id": 1232394}, {"name": "Органеллы", "id": 73636}, {"name": "Хромосомы", "id": 182231}, {"name": "Биологические_журналы", "id": 89280}, {"name": "Спиритуализм", "id": 1372916}, {"name": "Авторы_неакадемических_исследований_в_биологии", "id": 4598327}, {"name": "Криптиды", "id": 2228312}, {"name": "Охрана_окружающей_среды", "id": 57285}, {"name": "Экономика_окружающей_среды", "id": 7418330}, {"name": "Экосистемы", "id": 2654003}, {"name": "Размножение", "id": 345212}, {"name": "Фотосинтез", "id": 402365}, {"name": "Старение", "id": 821133}, {"name": "Патологические_процессы", "id": 928986}, {"name": "Клеточные_процессы", "id": 1136491}, {"name": "Персонажи,_обладающие_исцеляющим_фактором", "id": 4107673}, {"name": "Дыхание", "id": 89465}, {"name": "Метаболизм", "id": 371589}, {"name": "Организмы_по_алфавиту", "id": 2718151}, {"name": "Ферменты_по_алфавиту", "id": 4926233}, {"name": "Модельные_организмы", "id": 1623977}, {"name": "Организмы,_испускающие_биолюминесцентное_свечение", "id": 2394565}, {"name": "Лишайники", "id": 94616}, {"name": "Живые_ископаемые", "id": 1301295}, {"name": "Эволюция_групп_организмов", "id": 1947231}, {"name": "Анатомия", "id": 9032}, {"name": "Морфология_растений", "id": 191289}, {"name": "Морфология_грибов", "id": 1301446}, {"name": "Вирусы", "id": 9232}, {"name": "Бактериальные_инфекции", "id": 67213}, {"name": "Бактерии_по_алфавиту", "id": 576257}, {"name": "Грамположительные_бактерии", "id": 5731476}, {"name": "Грамотрицательные_бактерии", "id": 5731527}, {"name": "Таксоны_бактерий,_названные_в_честь_людей", "id": 5733333}, {"name": "Растения", "id": 10836}, {"name": "Археи_по_алфавиту", "id": 611834}, {"name": "Протисты_по_алфавиту", "id": 576259}, {"name": "Ядовитые_грибы", "id": 83119}, {"name": "Грибковые_заболевания", "id": 103991}, {"name": "Съедобные_грибы", "id": 150286}, {"name": "Грибы_по_алфавиту", "id": 575415}, {"name": "Несъедобные_грибы", "id": 663622}, {"name": "Лекарственные_грибы", "id": 5187681}, {"name": "Виды_грибов,_описанные_в_Systema_mycologicum", "id": 6249197}, {"name": "Анатомия_животных", "id": 190319}, {"name": "Поведение_животных", "id": 297835}, {"name": "Животные_по_алфавиту", "id": 575414}, {"name": "Личинки", "id": 1949353}, {"name": "Базидиомицеты", "id": 202724}, {"name": "Леканоромицеты", "id": 2411107}, {"name": "Taphrinomycotina", "id": 3480379}, {"name": "Круглые_черви", "id": 636467}, {"name": "Анатомия_членистоногих", "id": 139711}, {"name": "Вымершие_насекомые", "id": 2430424}, {"name": "Dinocarida", "id": 4841673}, {"name": "Акариазы", "id": 2752276}, {"name": "Энтомозы", "id": 2752958}, {"name": "Инсектициды", "id": 284786}, {"name": "Насекомые-вредители", "id": 1117632}, {"name": "Таксоны_насекомых,_названные_в_честь_людей", "id": 3618994}, {"name": "Паразиты_насекомых", "id": 4021235}, {"name": "Пещерные_насекомые", "id": 6416026}, {"name": "Высшие_раки", "id": 614672}, {"name": "Губоногие", "id": 2548063}, {"name": "Двупарноногие", "id": 4348288}, {"name": "Подёнки", "id": 1699528}, {"name": "Чешуекрылые", "id": 73281}, {"name": "Блохи", "id": 775221}, {"name": "Ручейники", "id": 775226}, {"name": "Длинноусые", "id": 2752803}, {"name": "Миазы", "id": 3663532}, {"name": "Вымершие_двукрылые", "id": 4876164}, {"name": "Роды_двукрылых", "id": 8570429}, {"name": "Stylops", "id": 8504359}, {"name": "Вымершие_сетчатокрылые", "id": 4879901}, {"name": "Муравьиные_львы", "id": 5102186}, {"name": "Вымершие_скорпионницы", "id": 5044557}, {"name": "Привиденьевые", "id": 1436121}, {"name": "Эмбии", "id": 2428249}, {"name": "Настоящие_кузнечики", "id": 3493048}, {"name": "Роды_прямокрылых", "id": 8588818}, {"name": "Symphypleona", "id": 3634482}, {"name": "Изотомиды", "id": 8403243}, {"name": "Мифические_животные-гибриды", "id": 6119113}, {"name": "Ктыри", "id": 1813001}, {"name": "Жужжала", "id": 2214854}, {"name": "Мухи-зеленушки", "id": 4259126}, {"name": "Tabaninae", "id": 7663842}, {"name": "Моллюски", "id": 22021}, {"name": "Многощетинковые_черви", "id": 2138006}, {"name": "Роды_кольчатых_червей", "id": 10731935}, {"name": "Трематоды", "id": 1571288}, {"name": "Богомоловые", "id": 2177751}, {"name": "Термиты", "id": 2299457}, {"name": "Ectobiidae", "id": 4890850}, {"name": "Роды_таракановых", "id": 8578581}, {"name": "Arenivaga", "id": 9123536}, {"name": "Равнокрылые_стрекозы", "id": 2342553}, {"name": "Роды_стрекоз", "id": 8574079}, {"name": "Настоящие_стрекозы", "id": 4035820}, {"name": "Сеноеды", "id": 1135894}, {"name": "Пухоеды_и_вши", "id": 2694957}, {"name": "Цикадовые", "id": 2588888}, {"name": "Роды_полужесткокрылых", "id": 8591389}, {"name": "Роды_трипсов", "id": 8590104}, {"name": "Thripidae", "id": 10043091}, {"name": "Pentatomomorpha", "id": 4239911}, {"name": "Настоящие_тли", "id": 7701610}, {"name": "Щитовки", "id": 5098135}, {"name": "Мучнистые_червецы", "id": 5098193}, {"name": "Ложнощитовки", "id": 5098254}, {"name": "Гребляки", "id": 4151376}, {"name": "Пеницилл", "id": 7594561}, {"name": "Таларомицес", "id": 7611484}, {"name": "Трилобиты_кембрийского_периода", "id": 7669965}, {"name": "Береговушки", "id": 4259188}, {"name": "Серые_мясные_мухи", "id": 4259138}, {"name": "Eristalinae", "id": 7699051}, {"name": "Syrphinae", "id": 7699053}, {"name": "Microdontinae", "id": 7699121}, {"name": "Списки_таксонов_пауков", "id": 1985243}, {"name": "Списки_бабочек", "id": 737440}, {"name": "Списки_таксонов_жуков", "id": 2720658}, {"name": "Вымершие_хрящевые_рыбы", "id": 2536105}, {"name": "Хвостоколообразные", "id": 5192055}, {"name": "Скатообразные", "id": 5267081}, {"name": "Нарциновые", "id": 4977022}, {"name": "Сомообразные", "id": 291692}, {"name": "Вымершие_лучепёрые_рыбы", "id": 5397865}, {"name": "Батрахообразные", "id": 7744622}, {"name": "Сельдевые", "id": 1550528}, {"name": "Тресковые", "id": 709545}, {"name": "Окуневидные", "id": 5590028}, {"name": "Карповые", "id": 237005}, {"name": "Осетровые", "id": 765929}, {"name": "Камбаловые", "id": 3672160}, {"name": "Харациновые", "id": 3353691}, {"name": "Семейства_хрящевых_рыб", "id": 5971277}, {"name": "Роды_хрящевых_рыб", "id": 10729904}, {"name": "Игловые", "id": 1511116}, {"name": "Рогатковые", "id": 3746075}, {"name": "Ставридовые", "id": 3908380}, {"name": "Губановые", "id": 2493927}, {"name": "Бычковые", "id": 1599200}, {"name": "Скорпеновые", "id": 33399}, {"name": "Спаровые", "id": 3668658}, {"name": "Цихловые", "id": 1385809}, {"name": "Птицы", "id": 8717}, {"name": "Морские_млекопитающие", "id": 1649161}, {"name": "Паразиты_млекопитающих", "id": 3965732}, {"name": "Полуводные_млекопитающие", "id": 250886}, {"name": "Фильмы_о_медведях", "id": 3621713}, {"name": "Безногие_земноводные", "id": 1792521}, {"name": "Ложноногие", "id": 1272612}, {"name": "Питоны", "id": 3938810}, {"name": "Ужеобразные", "id": 305483}, {"name": "Ямкоголовые", "id": 2157089}, {"name": "Хищные_сумчатые", "id": 2724851}, {"name": "Кенгуровые", "id": 1930619}, {"name": "Фильмы_про_обезьян", "id": 3627005}, {"name": "Летучие_мыши", "id": 188835}, {"name": "Крылановые", "id": 3640967}, {"name": "Вымершие_носороговые", "id": 4688492}, {"name": "Куньи", "id": 22013}, {"name": "Вымершие_медвежьи", "id": 2556959}, {"name": "Собаки", "id": 22007}, {"name": "Волки", "id": 775476}, {"name": "Кошачьи", "id": 22003}, {"name": "Знаменитые_собаки_по_алфавиту", "id": 10352034}, {"name": "Знаменитые_кошки", "id": 1411184}, {"name": "Белозубки", "id": 2191795}, {"name": "Бурозубки", "id": 2191852}, {"name": "Лошади", "id": 46205}, {"name": "Мифические_лошади", "id": 144880}, {"name": "Полорогие", "id": 53329}, {"name": "Оленевые", "id": 3712624}, {"name": "Китобойный_промысел", "id": 1518233}, {"name": "Дельфиновые", "id": 236899}, {"name": "Грызуны", "id": 34791}, {"name": "Вымершие_приматы", "id": 2512176}, {"name": "Вымышленные_кролики_и_зайцы", "id": 1390668}, {"name": "Зайцы", "id": 137482}, {"name": "Лемурообразные", "id": 1548181}, {"name": "Мартышковые", "id": 303182}, {"name": "Вымершие_гоминиды", "id": 7309517}, {"name": "Цепкохвостые_обезьяны", "id": 1404491}, {"name": "Саковые", "id": 1532514}, {"name": "Игрунковые", "id": 1548185}, {"name": "Паукообразные_обезьяны", "id": 2081540}, {"name": "Паразиты_человека", "id": 13489}, {"name": "Белки_человека", "id": 1787917}, {"name": "Синапсиды_пермского_периода", "id": 6960985}, {"name": "Синапсиды_триасового_периода", "id": 6960987}, {"name": "Млекопитающие_мелового_периода", "id": 4394832}, {"name": "Млекопитающие_неогена", "id": 5138114}, {"name": "Аспиды", "id": 81653}, {"name": "Гербы_с_изображением_медведей", "id": 9905925}, {"name": "Флаги_с_изображением_медведя", "id": 10022633}, {"name": "Гербы_с_изображением_оленя", "id": 9906662}, {"name": "Флаги_с_изображением_оленя", "id": 10018847}, {"name": "Гербы_с_изображением_лошади/коня", "id": 9906683}, {"name": "Флаги_с_изображением_лошади", "id": 9997197}, {"name": "Списки_птиц_по_странам", "id": 8065769}, {"name": "Списки_млекопитающих_по_странам", "id": 8066644}, {"name": "Списки_пресмыкающихся_по_странам", "id": 8085447}, {"name": "Списки_млекопитающих_по_регионам", "id": 3975793}, {"name": "Списки_муравьёв_по_странам", "id": 5162958}, {"name": "Списки_насекомых_Европы", "id": 9783605}, {"name": "Настоящие_саранчовые", "id": 1884582}, {"name": "Биологи_Великобритании", "id": 51947}, {"name": "Биологи_России", "id": 51949}, {"name": "Биологи_Германии", "id": 71613}, {"name": "Биологи_США", "id": 124005}, {"name": "Биологи_СССР", "id": 179784}, {"name": "Биологи_Франции", "id": 350303}, {"name": "Биологи_Украины", "id": 1040787}, {"name": "Палеонтологи_Германии", "id": 48253}, {"name": "Палеонтологи_России", "id": 93020}, {"name": "Палеонтологи_США", "id": 93023}, {"name": "Палеонтологи_Великобритании", "id": 157911}, {"name": "Палеонтологи_СССР", "id": 502749}, {"name": "Палеонтологи_Франции", "id": 1098172}, {"name": "Ботаники_Германии", "id": 51405}, {"name": "Ботаники_России", "id": 51838}, {"name": "Ботаники_Франции", "id": 56240}, {"name": "Ботаники_Австрии", "id": 56241}, {"name": "Ботаники_Чехии", "id": 89562}, {"name": "Ботаники_Швейцарии", "id": 89563}, {"name": "Ботаники_Великобритании", "id": 89565}, {"name": "Ботаники_Австралии", "id": 89566}, {"name": "Ботаники_Венгрии", "id": 89583}, {"name": "Ботаники_Украины", "id": 95026}, {"name": "Ботаники_Швеции", "id": 129354}, {"name": "Ботаники_Дании", "id": 179777}, {"name": "Ботаники_СССР", "id": 502590}, {"name": "Ботаники_США", "id": 651195}, {"name": "Ботаники_Испании", "id": 814990}, {"name": "Ботаники_Италии", "id": 923319}, {"name": "Ботаники_Японии", "id": 1016571}, {"name": "Ботаники_Польши", "id": 1040781}, {"name": "Ботаники_Финляндии", "id": 1210389}, {"name": "Ботаники_Бельгии", "id": 1298585}, {"name": "Ботаники_Нидерландов", "id": 1425460}, {"name": "Зоологи_Германии", "id": 51466}, {"name": "Зоологи_России", "id": 51467}, {"name": "Зоологи_Австрии", "id": 72512}, {"name": "Зоологи_Великобритании", "id": 72513}, {"name": "Зоологи_Франции", "id": 92237}, {"name": "Зоологи_Польши", "id": 97879}, {"name": "Зоологи_Швеции", "id": 173173}, {"name": "Зоологи_США", "id": 297056}, {"name": "Зоологи_СССР", "id": 604047}, {"name": "Зоологи_Украины", "id": 2416990}, {"name": "Энтомологи_России", "id": 82245}, {"name": "Энтомологи_США", "id": 274774}, {"name": "Энтомологи_Великобритании", "id": 283607}, {"name": "Энтомологи_Австрии", "id": 563189}, {"name": "Энтомологи_Германии", "id": 1074370}, {"name": "Энтомологи_СССР", "id": 1757068}, {"name": "Энтомологи_Италии", "id": 1867322}, {"name": "Энтомологи_Украины", "id": 2014526}, {"name": "Энтомологи_Франции", "id": 2051852}, {"name": "Экология_России", "id": 153250}, {"name": "Микробиологи_России", "id": 318902}, {"name": "Микробиологи_США", "id": 396008}, {"name": "Микробиологи_Германии", "id": 789336}, {"name": "Микробиологи_СССР", "id": 1036695}, {"name": "Вирусологи_США", "id": 757690}, {"name": "Вирусологи_СССР", "id": 757695}, {"name": "Вирусологи_России", "id": 757718}, {"name": "Генетики_России", "id": 182582}, {"name": "Генетики_СССР", "id": 207778}, {"name": "Генетики_США", "id": 761002}, {"name": "Генетики_Великобритании", "id": 761006}, {"name": "Орнитологи_Франции", "id": 909301}, {"name": "Орнитологи_Германии", "id": 2636950}, {"name": "Орнитологи_России", "id": 2637484}, {"name": "Орнитологи_Великобритании", "id": 2833358}, {"name": "Орнитологи_США", "id": 3186468}, {"name": "Орнитологи_СССР", "id": 3405693}, {"name": "Гидробиологи_России", "id": 2943765}, {"name": "Гидробиологи_СССР", "id": 3765763}, {"name": "Ихтиологи_России", "id": 2771969}, {"name": "Ихтиологи_СССР", "id": 4171667}, {"name": "Териологи_СССР", "id": 5026715}, {"name": "Геоботаники_России", "id": 6313250}, {"name": "Селекционеры_СССР", "id": 295067}, {"name": "Селекционеры_России", "id": 3731206}, {"name": "Растениеводы_СССР", "id": 6144031}, {"name": "Растениеводы_России", "id": 6305075}, {"name": "Паразитологи_СССР", "id": 6508144}, {"name": "Радиобиологи_СССР", "id": 6570802}, {"name": "Микологи_Франции", "id": 2639509}, {"name": "Микологи_США", "id": 2693432}, {"name": "Микологи_Германии", "id": 3267165}, {"name": "Микологи_Италии", "id": 3291116}, {"name": "Микологи_Великобритании", "id": 3688837}, {"name": "Микологи_СССР", "id": 3704259}, {"name": "Биологические_награды", "id": 1869004}, {"name": "Изображения:Биологи", "id": 362565}, {"name": "Члены_Лондонского_Линнеевского_общества", "id": 1213116}, {"name": "Популяризаторы_биологии", "id": 1995474}, {"name": "Доктора_биологических_наук", "id": 2115348}, {"name": "Ученики_Карла_Линнея", "id": 3195107}, {"name": "Кандидаты_биологических_наук", "id": 3414443}, {"name": "Биологи_по_алфавиту", "id": 3553326}, {"name": "Женщины-биологи", "id": 5723160}, {"name": "Естественнонаучные_музеи", "id": 631625}, {"name": "Экологические_организации", "id": 871768}, {"name": "Биологи_XX_века", "id": 2024072}, {"name": "Биологи_XIX_века", "id": 2024125}, {"name": "Биологи_XXI_века", "id": 2739678}, {"name": "Ботаники_XVI_века", "id": 1747065}, {"name": "Ботаники_XVII_века", "id": 1748885}, {"name": "Ботаники_XIX_века", "id": 2892199}, {"name": "Ботаники_XX_века", "id": 3045142}, {"name": "Ботаники_XVIII_века", "id": 3147873}, {"name": "Ботаники_XXI_века", "id": 3549202}, {"name": "Молекулярные_биологи", "id": 742098}, {"name": "Эволюционисты", "id": 1041225}, {"name": "Биотехнологи", "id": 1688633}, {"name": "Этологи", "id": 1984696}, {"name": "Цитологи", "id": 1984708}, {"name": "Фитопатологи", "id": 3611726}, {"name": "Награждённые_медалью_Линнея", "id": 2605190}, {"name": "Авторы_зоологических_таксонов", "id": 3320721}, {"name": "Зоологи_по_алфавиту", "id": 4491196}, {"name": "Карцинологи", "id": 7796411}, {"name": "Протозоологи", "id": 8252773}, {"name": "Исследователи_динозавров", "id": 10845129}, {"name": "Патофизиологи", "id": 2637016}, {"name": "Физиологи_по_алфавиту", "id": 3553236}, {"name": "Физиологи_растений", "id": 5181499}, {"name": "Биофизики_по_алфавиту", "id": 5607560}, {"name": "Биохимики_по_алфавиту", "id": 6501471}, {"name": "Биохимики_XX_века", "id": 6870374}, {"name": "Биохимики_XXI_века", "id": 7220035}, {"name": "Авторы_ботанических_таксонов", "id": 965691}, {"name": "Геоботаники", "id": 987224}, {"name": "Альгологи", "id": 1163766}, {"name": "Долиннеевские_ботаники", "id": 1213595}, {"name": "Птеридологи", "id": 1376529}, {"name": "Бриологи", "id": 1426910}, {"name": "Палеоботаники", "id": 1512175}, {"name": "Лауреаты_премии_имени_В._Л._Комарова", "id": 1854568}, {"name": "Лихенологи", "id": 2023319}, {"name": "Ботаники_по_алфавиту", "id": 2146946}, {"name": "Члены_Русского_ботанического_общества", "id": 4003760}, {"name": "Женщины-ботаники", "id": 7352611}, {"name": "Палеонтологи_по_алфавиту", "id": 3552989}, {"name": "Палеоантропологи", "id": 3947327}, {"name": "Ихтиологи_по_алфавиту", "id": 6779583}, {"name": "Микологи_по_алфавиту", "id": 6533935}, {"name": "Генетики_по_алфавиту", "id": 6502701}, {"name": "Генетики_XX_века", "id": 6818972}, {"name": "Генетики_XXI_века", "id": 7424065}, {"name": "Микробиологи_по_алфавиту", "id": 6536544}, {"name": "Эмбриологи_по_алфавиту", "id": 6567635}, {"name": "Биофизики_России", "id": 394167}, {"name": "Биофизики_США", "id": 791298}, {"name": "Биофизики_СССР", "id": 1109342}, {"name": "Биохимики_США", "id": 402334}, {"name": "Биохимики_России", "id": 402624}, {"name": "Биохимики_Германии", "id": 541750}, {"name": "Биохимики_Великобритании", "id": 541753}, {"name": "Биохимики_СССР", "id": 577261}, {"name": "Иммунологи_по_алфавиту", "id": 6619478}, {"name": "Нейробиологи_США", "id": 799429}, {"name": "Экологи_по_алфавиту", "id": 6292390}, {"name": "Специалисты_по_биоразнообразию", "id": 7290308}, {"name": "Экологи_России", "id": 153248}, {"name": "Экологи_США", "id": 651196}, {"name": "Экологи_СССР", "id": 2017229}, {"name": "Герпетологи_по_алфавиту", "id": 9275687}, {"name": "Палеонтологи_XIX_века", "id": 3553341}, {"name": "Палеонтологи_XX_века", "id": 3943254}, {"name": "Физиологи_XIX_века", "id": 5294390}, {"name": "Физиологи_XX_века", "id": 6830871}, {"name": "Физиологи_XXI_века", "id": 6830872}, {"name": "Зоологи_XIX_века", "id": 6313003}, {"name": "Зоологи_XX_века", "id": 6313038}, {"name": "Зоологи_XXI_века", "id": 6809432}, {"name": "Микробиологи_XX_века", "id": 6818592}, {"name": "Микробиологи_XXI_века", "id": 7419342}, {"name": "Лесоводы_XX_века", "id": 7568832}, {"name": "Селекционеры_XX_века", "id": 6818764}, {"name": "Геоботаники_СССР", "id": 6312582}, {"name": "Экологи_XXI_века", "id": 7583579}, {"name": "Экологи_XX_века", "id": 7593209}, {"name": "Герпетологи_XX_века", "id": 10087868}, {"name": "Семейства_пресмыкающихся", "id": 689100}, {"name": "Роды_пресмыкающихся", "id": 10722854}, {"name": "Семейства_земноводных", "id": 774271}, {"name": "Роды_земноводных", "id": 10730015}, {"name": "Роды_птиц", "id": 1757501}, {"name": "Роды_синапсид", "id": 10722989}, {"name": "Семейства_птиц", "id": 437362}, {"name": "Семейства_синапсид", "id": 5485041}, {"name": "Отряды_млекопитающих", "id": 2427978}, {"name": "Отряды_птиц", "id": 2428051}, {"name": "Семейства_млекопитающих", "id": 506303}, {"name": "Роды_млекопитающих", "id": 9913378}, {"name": "Животные,_описанные_в_1758_году", "id": 1554621}, {"name": "Животные,_описанные_в_2001_году", "id": 1554624}, {"name": "Животные,_описанные_в_2002_году", "id": 1554626}, {"name": "Животные,_описанные_в_2003_году", "id": 1554630}, {"name": "Животные,_описанные_в_2008_году", "id": 1554631}, {"name": "Животные,_описанные_в_1761_году", "id": 1554643}, {"name": "Животные,_описанные_в_1798_году", "id": 1554645}, {"name": "Животные,_описанные_в_1846_году", "id": 1554647}, {"name": "Животные,_описанные_в_1889_году", "id": 1554650}, {"name": "Животные,_описанные_в_1895_году", "id": 1554652}, {"name": "Животные,_описанные_в_1999_году", "id": 1554653}, {"name": "Животные,_описанные_в_1993_году", "id": 1554656}, {"name": "Животные,_описанные_в_1990_году", "id": 1554658}, {"name": "Животные,_описанные_в_1988_году", "id": 1554659}, {"name": "Животные,_описанные_в_1970_году", "id": 1554660}, {"name": "Животные,_описанные_в_1968_году", "id": 1554662}, {"name": "Животные,_описанные_в_1963_году", "id": 1554664}, {"name": "Животные,_описанные_в_1957_году", "id": 1554667}, {"name": "Животные,_описанные_в_1930_году", "id": 1554669}, {"name": "Животные,_описанные_в_1905_году", "id": 1554670}, {"name": "Животные,_описанные_в_1917_году", "id": 1554671}, {"name": "Животные,_описанные_в_1939_году", "id": 1554673}, {"name": "Животные,_описанные_в_1799_году", "id": 1554675}, {"name": "Животные,_описанные_в_1900_году", "id": 1554679}, {"name": "Животные,_описанные_в_1797_году", "id": 1554685}, {"name": "Животные,_описанные_в_1853_году", "id": 1554690}, {"name": "Животные,_описанные_в_1904_году", "id": 1554692}, {"name": "Животные,_описанные_в_1783_году", "id": 1554693}, {"name": "Животные,_описанные_в_1955_году", "id": 1554696}, {"name": "Животные,_описанные_в_1763_году", "id": 1554698}, {"name": "Животные,_описанные_в_1802_году", "id": 1554699}, {"name": "Животные,_описанные_в_1882_году", "id": 1554748}, {"name": "Животные,_описанные_в_1774_году", "id": 1554749}, {"name": "Животные,_описанные_в_1823_году", "id": 1554750}, {"name": "Животные,_описанные_в_1780_году", "id": 1554752}, {"name": "Животные,_описанные_в_1869_году", "id": 1554753}, {"name": "Животные,_описанные_в_1825_году", "id": 1554755}, {"name": "Животные,_описанные_в_1791_году", "id": 1554756}, {"name": "Животные,_описанные_в_1821_году", "id": 1554758}, {"name": "Животные,_описанные_в_1775_году", "id": 1554762}, {"name": "Животные,_описанные_в_1771_году", "id": 1554763}, {"name": "Животные,_описанные_в_1776_году", "id": 1554767}, {"name": "Животные,_описанные_в_1867_году", "id": 1554771}, {"name": "Животные,_описанные_в_1781_году", "id": 1558779}, {"name": "Животные,_описанные_в_1991_году", "id": 1558781}, {"name": "Животные,_описанные_в_1850_году", "id": 1558782}, {"name": "Животные,_описанные_в_1997_году", "id": 1566967}, {"name": "Животные,_описанные_в_2000_году", "id": 1654811}, {"name": "Животные,_описанные_в_1923_году", "id": 1675071}, {"name": "Животные,_описанные_в_1833_году", "id": 1675100}, {"name": "Животные,_описанные_в_1794_году", "id": 1743271}, {"name": "Животные,_описанные_в_1785_году", "id": 1743272}, {"name": "Животные,_описанные_в_1995_году", "id": 1748395}, {"name": "Животные,_описанные_в_1861_году", "id": 1796205}, {"name": "Животные,_описанные_в_1836_году", "id": 1802816}, {"name": "Животные,_описанные_в_1788_году", "id": 1802827}, {"name": "Животные,_описанные_в_1832_году", "id": 1802966}, {"name": "Животные,_описанные_в_1830_году", "id": 1802969}, {"name": "Животные,_описанные_в_1817_году", "id": 1803010}, {"name": "Животные,_описанные_в_1884_году", "id": 1804307}, {"name": "Животные,_описанные_в_1847_году", "id": 1806047}, {"name": "Животные,_описанные_в_1808_году", "id": 1806076}, {"name": "Животные,_описанные_в_1829_году", "id": 1806086}, {"name": "Животные,_описанные_в_1801_году", "id": 1806787}, {"name": "Животные,_описанные_в_1789_году", "id": 1806797}, {"name": "Животные,_описанные_в_1766_году", "id": 1807362}, {"name": "Животные,_описанные_в_1843_году", "id": 1807431}, {"name": "Животные,_описанные_в_1953_году", "id": 1812466}, {"name": "Животные,_описанные_в_1811_году", "id": 1814418}, {"name": "Животные,_описанные_в_1876_году", "id": 1814422}, {"name": "Животные,_описанные_в_1851_году", "id": 1814504}, {"name": "Животные,_описанные_в_1787_году", "id": 1814637}, {"name": "Животные,_описанные_в_1937_году", "id": 1815448}, {"name": "Животные,_описанные_в_1831_году", "id": 1815455}, {"name": "Животные,_описанные_в_1835_году", "id": 1819746}, {"name": "Животные,_описанные_в_1883_году", "id": 1823847}, {"name": "Животные,_описанные_в_1844_году", "id": 1829450}, {"name": "Животные,_описанные_в_1885_году", "id": 1829452}, {"name": "Животные,_описанные_в_1918_году", "id": 1829453}, {"name": "Животные,_описанные_в_1804_году", "id": 1829468}, {"name": "Животные,_описанные_в_1828_году", "id": 1829472}, {"name": "Животные,_описанные_в_1913_году", "id": 1829474}, {"name": "Животные,_описанные_в_1868_году", "id": 1829481}, {"name": "Животные,_описанные_в_1795_году", "id": 1829484}, {"name": "Животные,_описанные_в_1800_году", "id": 1829488}, {"name": "Животные,_описанные_в_1881_году", "id": 1829509}, {"name": "Животные,_описанные_в_1819_году", "id": 1829578}, {"name": "Животные,_описанные_в_1814_году", "id": 1829579}, {"name": "Животные,_описанные_в_1820_году", "id": 1829591}, {"name": "Животные,_описанные_в_1778_году", "id": 1829594}, {"name": "Животные,_описанные_в_1773_году", "id": 1829599}, {"name": "Животные,_описанные_в_1769_году", "id": 1829606}, {"name": "Животные,_описанные_в_1929_году", "id": 1829612}, {"name": "Животные,_описанные_в_1807_году", "id": 1829634}, {"name": "Животные,_описанные_в_1792_году", "id": 1829643}, {"name": "Животные,_описанные_в_1907_году", "id": 1829658}, {"name": "Животные,_описанные_в_1858_году", "id": 1829659}, {"name": "Животные,_описанные_в_1849_году", "id": 1829663}, {"name": "Животные,_описанные_в_1786_году", "id": 1829673}, {"name": "Животные,_описанные_в_1824_году", "id": 1829677}, {"name": "Животные,_описанные_в_1841_году", "id": 1829687}, {"name": "Животные,_описанные_в_1903_году", "id": 1829694}, {"name": "Животные,_описанные_в_1863_году", "id": 1829699}, {"name": "Животные,_описанные_в_1837_году", "id": 1829704}, {"name": "Животные,_описанные_в_1790_году", "id": 1829705}, {"name": "Животные,_описанные_в_1875_году", "id": 1829709}, {"name": "Животные,_описанные_в_1859_году", "id": 1829712}, {"name": "Животные,_описанные_в_1856_году", "id": 1829716}, {"name": "Животные,_описанные_в_1924_году", "id": 1829718}, {"name": "Животные,_описанные_в_1838_году", "id": 1829727}, {"name": "Животные,_описанные_в_1782_году", "id": 1829739}, {"name": "Животные,_описанные_в_1901_году", "id": 1829745}, {"name": "Животные,_описанные_в_1815_году", "id": 1829749}, {"name": "Животные,_описанные_в_1866_году", "id": 1829756}, {"name": "Животные,_описанные_в_1777_году", "id": 1829757}, {"name": "Животные,_описанные_в_1842_году", "id": 1829763}, {"name": "Животные,_описанные_в_1779_году", "id": 1829772}, {"name": "Животные,_описанные_в_1827_году", "id": 1829775}, {"name": "Животные,_описанные_в_1812_году", "id": 1829794}, {"name": "Животные,_описанные_в_1839_году", "id": 1829812}, {"name": "Животные,_описанные_в_1826_году", "id": 1829816}, {"name": "Животные,_описанные_в_1816_году", "id": 1829822}, {"name": "Животные,_описанные_в_1878_году", "id": 1829855}, {"name": "Животные,_описанные_в_1941_году", "id": 1829908}, {"name": "Животные,_описанные_в_1793_году", "id": 1829912}, {"name": "Животные,_описанные_в_1840_году", "id": 1829922}, {"name": "Животные,_описанные_в_1877_году", "id": 1829927}, {"name": "Животные,_описанные_в_1768_году", "id": 1829929}, {"name": "Животные,_описанные_в_1857_году", "id": 1829934}, {"name": "Животные,_описанные_в_1822_году", "id": 1829941}, {"name": "Животные,_описанные_в_1834_году", "id": 1829946}, {"name": "Животные,_описанные_в_1911_году", "id": 1829953}, {"name": "Животные,_описанные_в_1896_году", "id": 1829962}, {"name": "Животные,_описанные_в_1770_году", "id": 1829980}, {"name": "Животные,_описанные_в_1809_году", "id": 1830096}, {"name": "Животные,_описанные_в_1967_году", "id": 1830106}, {"name": "Животные,_описанные_в_1865_году", "id": 1830114}, {"name": "Животные,_описанные_в_1892_году", "id": 1830125}, {"name": "Животные,_описанные_в_1874_году", "id": 1830126}, {"name": "Животные,_описанные_в_1855_году", "id": 1830155}, {"name": "Животные,_описанные_в_2005_году", "id": 1830211}, {"name": "Животные,_описанные_в_1862_году", "id": 1830931}, {"name": "Животные,_описанные_в_1922_году", "id": 1830993}, {"name": "Животные,_описанные_в_1908_году", "id": 1830997}, {"name": "Животные,_описанные_в_1989_году", "id": 1831019}, {"name": "Животные,_описанные_в_1915_году", "id": 1831041}, {"name": "Животные,_описанные_в_1978_году", "id": 1831052}, {"name": "Животные,_описанные_в_1952_году", "id": 1831068}, {"name": "Животные,_описанные_в_2004_году", "id": 1831181}, {"name": "Животные,_описанные_в_1986_году", "id": 1831200}, {"name": "Животные,_описанные_в_1890_году", "id": 1831206}, {"name": "Животные,_описанные_в_1969_году", "id": 1831215}, {"name": "Животные,_описанные_в_1972_году", "id": 1831223}, {"name": "Животные,_описанные_в_1985_году", "id": 1831228}, {"name": "Животные,_описанные_в_1912_году", "id": 1831256}, {"name": "Животные,_описанные_в_1994_году", "id": 1831354}, {"name": "Животные,_описанные_в_2007_году", "id": 1831365}, {"name": "Животные,_описанные_в_1977_году", "id": 1831376}, {"name": "Животные,_описанные_в_1872_году", "id": 1831385}, {"name": "Животные,_описанные_в_1962_году", "id": 1831397}, {"name": "Животные,_описанные_в_2009_году", "id": 1831415}, {"name": "Животные,_описанные_в_1959_году", "id": 1831440}, {"name": "Животные,_описанные_в_1983_году", "id": 1831497}, {"name": "Животные,_описанные_в_1891_году", "id": 1831505}, {"name": "Животные,_описанные_в_1975_году", "id": 1831527}, {"name": "Животные,_описанные_в_1981_году", "id": 1831553}, {"name": "Животные,_описанные_в_1954_году", "id": 1831569}, {"name": "Животные,_описанные_в_1979_году", "id": 1831590}, {"name": "Животные,_описанные_в_1910_году", "id": 1833228}, {"name": "Животные,_описанные_в_1925_году", "id": 1833314}, {"name": "Животные,_описанные_в_1880_году", "id": 1833346}, {"name": "Животные,_описанные_в_1984_году", "id": 1833497}, {"name": "Животные,_описанные_в_1864_году", "id": 1833501}, {"name": "Животные,_описанные_в_1852_году", "id": 1833508}, {"name": "Животные,_описанные_в_1934_году", "id": 1833509}, {"name": "Животные,_описанные_в_1950_году", "id": 1833513}, {"name": "Животные,_описанные_в_1933_году", "id": 1833515}, {"name": "Животные,_описанные_в_1873_году", "id": 1833516}, {"name": "Животные,_описанные_в_1935_году", "id": 1833518}, {"name": "Животные,_описанные_в_1932_году", "id": 1833520}, {"name": "Животные,_описанные_в_1871_году", "id": 1833521}, {"name": "Животные,_описанные_в_1899_году", "id": 1833522}, {"name": "Животные,_описанные_в_1973_году", "id": 1833523}, {"name": "Животные,_описанные_в_1879_году", "id": 1833525}, {"name": "Животные,_описанные_в_1870_году", "id": 1833529}, {"name": "Животные,_описанные_в_1886_году", "id": 1833550}, {"name": "Животные,_описанные_в_1940_году", "id": 1833559}, {"name": "Животные,_описанные_в_1958_году", "id": 1833561}, {"name": "Животные,_описанные_в_1996_году", "id": 1835924}, {"name": "Животные,_описанные_в_1998_году", "id": 1835932}, {"name": "Животные,_описанные_в_1914_году", "id": 1835954}, {"name": "Животные,_описанные_в_2006_году", "id": 1836067}, {"name": "Животные,_описанные_в_1818_году", "id": 1837942}, {"name": "Животные,_описанные_в_1860_году", "id": 1838084}, {"name": "Животные,_описанные_в_1848_году", "id": 1838123}, {"name": "Животные,_описанные_в_1764_году", "id": 1841561}, {"name": "Животные,_описанные_в_1803_году", "id": 1841577}, {"name": "Животные,_описанные_в_1767_году", "id": 1841579}, {"name": "Животные,_описанные_в_1854_году", "id": 1841609}, {"name": "Животные,_описанные_в_1810_году", "id": 1842774}, {"name": "Животные,_описанные_в_1936_году", "id": 1842859}, {"name": "Животные,_описанные_в_1813_году", "id": 1842863}, {"name": "Животные,_описанные_в_1927_году", "id": 1868820}, {"name": "Животные,_описанные_в_1806_году", "id": 1882428}, {"name": "Животные,_описанные_в_1897_году", "id": 1882443}, {"name": "Животные,_описанные_в_1784_году", "id": 1882479}, {"name": "Животные,_описанные_в_1980_году", "id": 1883463}, {"name": "Животные,_описанные_в_1893_году", "id": 1884459}, {"name": "Животные,_описанные_в_1845_году", "id": 1884801}, {"name": "Животные,_описанные_в_1888_году", "id": 1884815}, {"name": "Животные,_описанные_в_1894_году", "id": 1884873}, {"name": "Животные,_описанные_в_1887_году", "id": 1884876}, {"name": "Животные,_описанные_в_1906_году", "id": 1884877}, {"name": "Животные,_описанные_в_1805_году", "id": 1884890}, {"name": "Животные,_описанные_в_1921_году", "id": 1884904}, {"name": "Животные,_описанные_в_1951_году", "id": 1887734}, {"name": "Животные,_описанные_в_1902_году", "id": 1889296}, {"name": "Животные,_описанные_в_1909_году", "id": 1889831}, {"name": "Животные,_описанные_в_1931_году", "id": 1889930}, {"name": "Животные,_описанные_в_1971_году", "id": 1889931}, {"name": "Животные,_описанные_в_1974_году", "id": 1889942}, {"name": "Животные,_описанные_в_1928_году", "id": 1889961}, {"name": "Животные,_описанные_в_1966_году", "id": 1889987}, {"name": "Животные,_описанные_в_1916_году", "id": 1889993}, {"name": "Животные,_описанные_в_1920_году", "id": 1890007}, {"name": "Животные,_описанные_в_1982_году", "id": 1903396}, {"name": "Животные,_описанные_в_2010_году", "id": 2245599}, {"name": "Животные,_описанные_в_1898_году", "id": 2255501}, {"name": "Животные,_описанные_в_1919_году", "id": 2255506}, {"name": "Животные,_описанные_в_1938_году", "id": 2255510}, {"name": "Животные,_описанные_в_1948_году", "id": 2255515}, {"name": "Животные,_описанные_в_1965_году", "id": 2255517}, {"name": "Животные,_описанные_в_1976_году", "id": 2255519}, {"name": "Животные,_описанные_в_1961_году", "id": 2324970}, {"name": "Животные,_описанные_в_1956_году", "id": 2341837}, {"name": "Животные,_описанные_в_1992_году", "id": 2349835}, {"name": "Животные,_описанные_в_1987_году", "id": 2432662}, {"name": "Животные,_описанные_в_1926_году", "id": 2448453}, {"name": "Животные,_описанные_в_1942_году", "id": 2530603}, {"name": "Животные,_описанные_в_1964_году", "id": 2743466}, {"name": "Животные,_описанные_в_1949_году", "id": 2757134}, {"name": "Животные,_описанные_в_2011_году", "id": 3172956}, {"name": "Животные,_описанные_в_1960_году", "id": 3436275}, {"name": "Животные,_описанные_в_2012_году", "id": 3585113}, {"name": "Животные,_описанные_в_2013_году", "id": 4287370}, {"name": "Животные,_описанные_в_2014_году", "id": 4859097}, {"name": "Животные,_описанные_в_2015_году", "id": 5398892}, {"name": "Животные,_описанные_в_2016_году", "id": 6165723}, {"name": "Животные,_описанные_в_2017_году", "id": 6727182}, {"name": "Животные,_описанные_в_2018_году", "id": 7302864}, {"name": "Животные,_описанные_в_2019_году", "id": 7726109}, {"name": "Животные,_описанные_в_2020_году", "id": 8151348}, {"name": "Животные,_описанные_в_2021_году", "id": 8648694}, {"name": "Животные,_описанные_в_2022_году", "id": 9160048}, {"name": "Животные,_описанные_в_2023_году", "id": 10023248}, {"name": "Животные,_описанные_в_2024_году", "id": 10481125}, {"name": "Грибы_Африки", "id": 2490552}, {"name": "Грибы_Азии", "id": 2490564}, {"name": "Грибы_Европы", "id": 2491491}, {"name": "Грибы_Америки", "id": 2495175}]}