{"name": "Древний_мир", "id": 9203, "predecessors": [{"name": "Всё", "id": 16350}], "successors": [{"name": "Древние_народы", "id": 258527}, {"name": "Древние_города", "id": 721068}, {"name": "Исторические_государства_Древнего_мира", "id": 1936611}, {"name": "Древний_Рим", "id": 11334}, {"name": "Древняя_Греция", "id": 12577}, {"name": "Античная_философия", "id": 35907}, {"name": "Гностицизм", "id": 66620}, {"name": "Античное_оружие", "id": 2256603}, {"name": "Армянская_мифология", "id": 29499}, {"name": "Римская_мифология", "id": 51426}, {"name": "Древнегреческая_мифология", "id": 377753}, {"name": "Древнеегипетская_мифология", "id": 3972787}, {"name": "Гунны", "id": 131240}, {"name": "Культура_Древней_Греции", "id": 52886}, {"name": "Культура_Древнего_Рима", "id": 52907}, {"name": "Культура_Древнего_Египта", "id": 93976}, {"name": "Древние_языки", "id": 109400}, {"name": "Древние_единицы_измерения", "id": 4380281}, {"name": "Литература_Византии", "id": 33560}, {"name": "Архитектура_Византии", "id": 889489}, {"name": "Византийские_ранги", "id": 1723464}, {"name": "Римское_право", "id": 131569}, {"name": "Право_Древней_Греции", "id": 1414612}, {"name": "Историки_Византии", "id": 62534}, {"name": "Философы_Византии", "id": 139044}, {"name": "Племена_Галлии", "id": 1796935}, {"name": "Ассирийские_правители", "id": 379018}, {"name": "Персоналии:Древняя_Македония", "id": 3612755}, {"name": "Патристика", "id": 1465735}, {"name": "Династия_Константина", "id": 1482391}, {"name": "Государство_Сасанидов", "id": 4883270}, {"name": "Историки_Поздней_античности", "id": 5687481}, {"name": "Историки_Древнего_Рима", "id": 51884}, {"name": "Философы_Древнего_Рима", "id": 52921}, {"name": "Философия_Древней_Греции", "id": 95443}, {"name": "Родившиеся_в_Галлии", "id": 3751495}, {"name": "Пеплумы", "id": 2256910}, {"name": "Фильмы_о_Древнем_Риме", "id": 2276628}, {"name": "Фильмы_о_Древнем_Египте", "id": 2713844}, {"name": "Древний_Рим_в_культуре_и_искусстве", "id": 3942087}, {"name": "История_Древнего_Рима", "id": 4333621}, {"name": "Навигационные_шаблоны:Древний_мир", "id": 4634384}, {"name": "Шаблоны:Внешние_ссылки:История:Древний_Рим", "id": 4598721}, {"name": "Шаблоны:Книги_по_истории_Древнего_Рима", "id": 4634513}, {"name": "Навигационные_шаблоны:Древний_Рим", "id": 7883787}, {"name": "Месопотамские_боги", "id": 3969073}, {"name": "Боспорское_царство", "id": 7247904}, {"name": "Скифы", "id": 52914}, {"name": "Хазарский_каганат", "id": 89339}, {"name": "Сарматы", "id": 476640}, {"name": "Персоналии:Золотая_Орда", "id": 129377}, {"name": "Монголо-татарское_иго", "id": 4286337}, {"name": "Архитектура_Древней_Греции", "id": 93996}, {"name": "Архитектура_Древнего_Рима", "id": 288356}, {"name": "Здания_и_сооружения_Древнего_Рима", "id": 6471128}, {"name": "Египетские_пирамиды", "id": 342950}, {"name": "Херсонес_Таврический", "id": 755212}, {"name": "Военачальники_Древнего_Рима", "id": 79284}, {"name": "Военачальники_Ахеменидов", "id": 6360368}, {"name": "Военачальники_Карфагена", "id": 6621605}, {"name": "Военачальники_III_века_до_н._э.", "id": 7068552}, {"name": "Военачальники_II_века_до_н._э.", "id": 7068585}, {"name": "Военачальники_IV_века_до_н._э.", "id": 7087451}, {"name": "Военачальники_V_века_до_н._э.", "id": 7088281}, {"name": "Военачальники_IV_века", "id": 7261150}, {"name": "Военачальники_I_века_до_н._э.", "id": 7422246}, {"name": "Военачальники_Спарты", "id": 195167}, {"name": "Военачальники_Афин", "id": 196168}, {"name": "Флотоводцы_Древней_Греции", "id": 231357}, {"name": "Диадохи", "id": 284209}, {"name": "Государственные_деятели_V_века_до_н._э.", "id": 7795959}, {"name": "Консулы-суффекты", "id": 2797854}, {"name": "Списки:Древний_Рим", "id": 2286871}, {"name": "Города_Золотой_Орды", "id": 1304315}, {"name": "Сражения_Золотой_Орды", "id": 953861}, {"name": "Скульпторы_Древней_Греции", "id": 79693}, {"name": "Пураны", "id": 984104}, {"name": "Веданта", "id": 650225}, {"name": "Махабхарата", "id": 107048}, {"name": "Упанишады", "id": 1112217}, {"name": "Сатрапы_империи_Александра_Македонского", "id": 6590797}, {"name": "Ахеменидские_сатрапы", "id": 7327052}, {"name": "Женщины_Ветхого_Завета", "id": 1232091}, {"name": "Женщины_Древнего_Рима", "id": 1452275}, {"name": "Женщины_Нового_Завета", "id": 1869215}, {"name": "Женщины_Древней_Греции", "id": 6002644}, {"name": "Женщины_IV_века", "id": 7671275}, {"name": "Супруги_правителей_IV_века_до_н._э.", "id": 2036546}, {"name": "Супруги_правителей_III_века_до_н._э.", "id": 2036543}, {"name": "Позднеантичные_язычники", "id": 10036865}, {"name": "Префекты_претория_эпохи_домината", "id": 1936490}, {"name": "Магистры_оффиций", "id": 3304081}, {"name": "Древнее_Средиземноморье", "id": 249208}, {"name": "Эллинистические_философы", "id": 8380048}, {"name": "Македонские_цари", "id": 175235}, {"name": "Боспорские_цари", "id": 565835}, {"name": "Цари_государства_Селевкидов", "id": 4113112}, {"name": "Вооружённые_силы_Древнего_Рима", "id": 972707}, {"name": "Войны_Древней_Греции", "id": 54327}, {"name": "Войны_Древнего_Рима", "id": 54330}, {"name": "Сражения_Римской_республики", "id": 369836}, {"name": "Сражения_III_века_до_н._э.", "id": 1842017}, {"name": "Сражения_Древней_Греции", "id": 3516612}, {"name": "Сражения_Пелопоннесской_войны", "id": 1842154}, {"name": "Военачальники_Александра_Македонского", "id": 2866433}]}