{"name": "Военно-воздушные_силы_СССР", "id": 967561, "predecessors": [{"name": "Вооружённые_силы_СССР", "id": 48835}, {"name": "Военно-воздушные_силы_по_странам", "id": 967629}, {"name": "История_авиации", "id": 312212}, {"name": "Авиация", "id": 8671}], "successors": [{"name": "Авиационные_происшествия_ВВС_СССР", "id": 4537898}, {"name": "Военные_аэродромы_СССР", "id": 6197674}, {"name": "Авиация_дальнего_действия_СССР", "id": 8207202}, {"name": "Морская_авиация_СССР_во_время_Великой_Отечественной_войны", "id": 2442227}, {"name": "Воевавшие_в_ВВС_СССР_во_время_Великой_Отечественной_войны", "id": 3346860}, {"name": "Лётчики_Великой_Отечественной_войны", "id": 1766404}, {"name": "Военные_лётчики_СССР", "id": 4791764}, {"name": "Военные_лётчики_1-го_класса", "id": 5920236}, {"name": "Военные_лётчики_2-го_класса", "id": 5920309}, {"name": "Командующие_воздушными_армиями_СССР", "id": 6165637}, {"name": "Командующие_ВВС_округов", "id": 7852047}, {"name": "Воздушные_армии_СССР", "id": 4022395}, {"name": "Авиационные_полки_ВВС_СССР", "id": 4244294}, {"name": "Авиационные_дивизии_СССР", "id": 2843716}, {"name": "Авиационные_формирования_СССР_в_Корейской_войне", "id": 5740458}]}